eesampling/__init__.py
eesampling/__version__.py
eesampling/bin_selection.py
eesampling/bins.py
eesampling/diagnostics.py
eesampling/equivalence.py
eesampling/model.py
eesampling/synthetic_data.py
eesampling-0.10.1.dist-info/DESCRIPTION.rst
eesampling-0.10.1.dist-info/METADATA
eesampling-0.10.1.dist-info/RECORD
eesampling-0.10.1.dist-info/WHEEL
eesampling-0.10.1.dist-info/metadata.json
eesampling-0.10.1.dist-info/top_level.txt
